lapy/__init__.py
lapy/_read_geometry.py
lapy/_tet_io.py
lapy/_tria_io.py
lapy/_version.py
lapy/conformal.py
lapy/diffgeo.py
lapy/heat.py
lapy/io.py
lapy/plot.py
lapy/polygon.py
lapy/shapedna.py
lapy/solver.py
lapy/tet_mesh.py
lapy/tria_mesh.py
lapy/commands/__init__.py
lapy/commands/sys_info.py
lapy/utils/__init__.py
lapy/utils/_config.py
lapy/utils/_imports.py
lapy-1.5.0.dist-info/licenses/LICENSE
lapy-1.5.0.dist-info/METADATA
lapy-1.5.0.dist-info/WHEEL
lapy-1.5.0.dist-info/entry_points.txt
lapy-1.5.0.dist-info/top_level.txt
lapy-1.5.0.dist-info/RECORD
