Metadata-Version: 2.4
Name: lapy
Version: 1.5.0
Summary: A package for differential geometry on meshes (Laplace, FEM)
Author-email: Martin Reuter <martin.reuter@dzne.de>
Maintainer-email: Martin Reuter <martin.reuter@dzne.de>
License: MIT License
Project-URL: homepage, https://Deep-MI.github.io/LaPy/dev/index.html
Project-URL: documentation, https://Deep-MI.github.io/LaPy/dev/index.html
Project-URL: source, https://github.com/Deep-MI/LaPy
Project-URL: tracker, https://github.com/Deep-MI/LaPy/issues
Keywords: python,Laplace,FEM,ShapeDNA,BrainPrint,Triangle Mesh,Tetrahedra Mesh,Geodesics in Heat,Mean Curvature Flow
Classifier: Operating System :: Microsoft :: Windows
Classifier: Operating System :: Unix
Classifier: Operating System :: MacOS
Classifier: Programming Language :: Python :: 3 :: Only
Classifier: Programming Language :: Python :: 3.9
Classifier: Programming Language :: Python :: 3.10
Classifier: Programming Language :: Python :: 3.11
Classifier: Programming Language :: Python :: 3.12
Classifier: Natural Language :: English
Classifier: License :: OSI Approved :: MIT License
Classifier: Intended Audience :: Science/Research
Requires-Python: >=3.9
License-File: LICENSE
Requires-Dist: nibabel
Requires-Dist: numpy>=1.21
Requires-Dist: plotly
Requires-Dist: psutil
Requires-Dist: scipy!=1.13.0
Provides-Extra: build
Requires-Dist: build; extra == "build"
Requires-Dist: twine; extra == "build"
Provides-Extra: chol
Requires-Dist: scikit-sparse>=0.4.16; extra == "chol"
Provides-Extra: doc
Requires-Dist: furo!=2023.8.17; extra == "doc"
Requires-Dist: matplotlib; extra == "doc"
Requires-Dist: memory-profiler; extra == "doc"
Requires-Dist: numpydoc; extra == "doc"
Requires-Dist: sphinx!=7.2.*; extra == "doc"
Requires-Dist: sphinxcontrib-bibtex; extra == "doc"
Requires-Dist: sphinx-copybutton; extra == "doc"
Requires-Dist: sphinx-design; extra == "doc"
Requires-Dist: sphinx-gallery; extra == "doc"
Requires-Dist: sphinx-issues; extra == "doc"
Requires-Dist: pypandoc; extra == "doc"
Requires-Dist: nbsphinx; extra == "doc"
Requires-Dist: IPython; extra == "doc"
Requires-Dist: ipykernel; extra == "doc"
Provides-Extra: style
Requires-Dist: bibclean; extra == "style"
Requires-Dist: codespell; extra == "style"
Requires-Dist: pydocstyle[toml]; extra == "style"
Requires-Dist: ruff; extra == "style"
Provides-Extra: test
Requires-Dist: pytest; extra == "test"
Requires-Dist: pytest-cov; extra == "test"
Requires-Dist: pytest-timeout; extra == "test"
Provides-Extra: all
Requires-Dist: lapy[build]; extra == "all"
Requires-Dist: lapy[chol]; extra == "all"
Requires-Dist: lapy[doc]; extra == "all"
Requires-Dist: lapy[style]; extra == "all"
Requires-Dist: lapy[test]; extra == "all"
Provides-Extra: full
Requires-Dist: lapy[all]; extra == "full"
Dynamic: license-file
